reflexDash/reflex.py
reflexDash/reflexTabs.py
reflexDash/confFiles/devices_reflex_v1.ods
reflexDash/confFiles/logVersionReflex_user.md
reflexDash/confFiles/palettes.pkl
reflexDash/confFiles/plc_reflex_v1.ods
reflexDash/confFiles/reflex_conffiles.pkl
reflexDash/confFiles/reflex_configfiles.ods
reflexDash/confFiles/pictures/logo_sylfen.png
reflexDash-0.1.1.dist-info/METADATA
reflexDash-0.1.1.dist-info/WHEEL
reflexDash-0.1.1.dist-info/top_level.txt
reflexDash-0.1.1.dist-info/RECORD
