Metadata-Version: 2.1
Name: reflexDash
Version: 0.1.1
Summary: source codes and configuration files to monitor small power data
Home-page: UNKNOWN
Author: Dorian Drevon
Author-email: drevondorian@gmail.com
License: UNKNOWN
Platform: UNKNOWN
Classifier: Programming Language :: Python :: 3
Classifier: License :: OSI Approved :: MIT License
Classifier: Operating System :: OS Independent
Requires-Python: >=3.8
Requires-Dist: dorianUtilsModulaire (==4.0.10)
